.gitignore
.travis.yml
CHANGES.rst
LICENSE.txt
README.md
pyproject.toml
setup.cfg
setup.py
.github/workflows/publish-to-pypi.yml
.github/workflows/python-package.yml
examples/demo-jwst.ipynb
examples/demo.ipynb
mastquery/__init__.py
mastquery/fetch.py
mastquery/jwst.py
mastquery/overlaps.py
mastquery/plot_utils.py
mastquery/query.py
mastquery/utils.py
mastquery/version.py
mastquery.egg-info/PKG-INFO
mastquery.egg-info/SOURCES.txt
mastquery.egg-info/dependency_links.txt
mastquery.egg-info/requires.txt
mastquery.egg-info/top_level.txt
mastquery/tests/__init__.py
mastquery/tests/test_jwst.py
mastquery/tests/test_query.py
mastquery/tests/test_utils.py