Metadata-Version: 2.1
Name: mastquery
Version: 1.7.1
Summary: Python tools for querying the MAST Archive
Home-page: https://github.com/gbrammer/mastquery
Author: G. Brammer
License: MIT
Project-URL: Source, https://github.com/gbrammer/mastquery
Project-URL: Tracker, https://github.com/gbrammer/mastquery/issues
Classifier: Development Status :: 3 - Alpha
Classifier: Intended Audience :: Science/Research
Classifier: Topic :: Scientific/Engineering :: Astronomy
Requires-Python: >=3.7
Provides-Extra: test
License-File: LICENSE.txt
